
[
    {
        "lastUnlock": "2014-10-29T05:29:21.8756697Z",
        "titleId": 1331147,
        "serviceConfigId": "054b0100-2668-415d-b546-f5f300144fcb",
        "titleType": "LiveApp",
        "platform": "Durango",
        "name": "ESPN",
        "earnedAchievements": 2,
        "currentGamerscore": 0,
        "maxGamerscore": 0
    },
    {
        "lastUnlock": "2017-04-02T09:08:18.1840000Z",
        "titleId": 19615130,
        "serviceConfigId": "169f0100-035a-4cfb-9e87-4506012b4d9a",
        "titleType": "DGame",
        "platform": "Durango",
        "name": "Super Mega Baseball: Extra Innings",
        "earnedAchievements": 1,
        "currentGamerscore": 5,
        "maxGamerscore": 1000
    },
    {
        "lastUnlock": "2016-12-20T05:06:27.1840000Z",
        "titleId": 23570566,
        "serviceConfigId": "3a6b0100-2314-41ab-a925-13680167a886",
        "titleType": "DGame",
        "platform": "Durango",
        "name": "Batman - The Telltale Series - Episode 1: Realm of Shadows",
        "earnedAchievements": 30,
        "currentGamerscore": 1000,
        "maxGamerscore": 1000
    },
    {
        "lastUnlock": "2017-05-11T00:29:39.3970000Z",
        "titleId": 37469967,
        "serviceConfigId": "d85e0100-5f9b-4797-a576-7e6d023bbf0f",
        "titleType": "DGame",
        "platform": "Durango",
        "name": "NBA Playgrounds",
        "earnedAchievements": 3,
        "currentGamerscore": 150,
        "maxGamerscore": 1000
    },
    {
        "lastUnlock": "2017-07-06T06:27:23.8740000Z",
        "titleId": 60633334,
        "serviceConfigId": "19cc0100-593c-414a-b461-a4cb039d30f6",
        "titleType": "DGame",
        "platform": "Durango",
        "name": "7 Days to Die",
        "earnedAchievements": 1,
        "currentGamerscore": 15,
        "maxGamerscore": 1000
    },
    {
        "lastUnlock": "2017-05-23T06:37:04.1260000Z",
        "titleId": 62572131,
        "serviceConfigId": "54240100-7870-4a47-8cec-7cfd03bac663",
        "titleType": "DGame",
        "platform": "Durango",
        "name": "The Wolf Among Us",
        "earnedAchievements": 31,
        "currentGamerscore": 760,
        "maxGamerscore": 1000
    },
    {
        "lastUnlock": "2017-01-26T06:59:59.6350000Z",
        "titleId": 74304278,
        "serviceConfigId": "e2f10100-3928-4019-8789-5f12046dcb16",
        "titleType": "DGame",
        "platform": "Durango",
        "name": "Tom Clancy's The Division",
        "earnedAchievements": 46,
        "currentGamerscore": 880,
        "maxGamerscore": 1450
    },
    {
        "lastUnlock": "2015-11-27T04:52:41.1798055Z",
        "titleId": 80579825,
        "serviceConfigId": "f4ad0100-febf-441e-9f12-5f1204cd8cf1",
        "titleType": "DGame",
        "platform": "Durango",
        "name": "Call of Duty: Black Ops III",
        "earnedAchievements": 19,
        "currentGamerscore": 360,
        "maxGamerscore": 1950
    },
    {
        "lastUnlock": "2017-06-04T04:39:32.8350000Z",
        "titleId": 85494077,
        "serviceConfigId": "2eba0100-c9de-47f7-bfaa-6def0518893d",
        "titleType": "DGame",
        "platform": "Durango",
        "name": "Microsoft Solitaire Collection",
        "earnedAchievements": 17,
        "currentGamerscore": 370,
        "maxGamerscore": 1000
    },
    {
        "lastUnlock": "2017-01-22T10:26:27.0090000Z",
        "titleId": 119262432,
        "serviceConfigId": "69cc0100-a99c-4b5a-9e86-05c5071bcce0",
        "titleType": "DGame",
        "platform": "Durango",
        "name": "The Jackbox Party Pack 3",
        "earnedAchievements": 6,
        "currentGamerscore": 300,
        "maxGamerscore": 1000
    },
    {
        "lastUnlock": "2016-11-10T03:09:11.5419416Z",
        "titleId": 122001257,
        "serviceConfigId": "64c10100-3d40-49d5-8f1c-c99807459769",
        "titleType": "LiveApp",
        "platform": "Durango",
        "name": "YouTube",
        "earnedAchievements": 5,
        "currentGamerscore": 0,
        "maxGamerscore": 0
    },
    {
        "lastUnlock": "2014-01-27T07:36:20.6360234Z",
        "titleId": 142841733,
        "serviceConfigId": "59df0100-c715-4530-a64f-15c708839785",
        "titleType": "DGame",
        "platform": "Durango",
        "name": "Madden NFL 25",
        "earnedAchievements": 17,
        "currentGamerscore": 260,
        "maxGamerscore": 1000
    },
    {
        "lastUnlock": "2017-10-05T02:40:25.0090000Z",
        "titleId": 144389848,
        "serviceConfigId": "bcc90100-31ff-42bd-b545-90cd089b36d8",
        "titleType": "DGame",
        "platform": "Durango",
        "name": "Destiny 2",
        "earnedAchievements": 3,
        "currentGamerscore": 140,
        "maxGamerscore": 1000
    },
    {
        "lastUnlock": "2015-11-16T04:31:38.1733689Z",
        "titleId": 219630713,
        "serviceConfigId": "1370999b-fca2-4c53-8ec5-73493bcb67e5",
        "titleType": "DGame",
        "platform": "Durango",
        "name": "Halo 5: Guardians",
        "earnedAchievements": 25,
        "currentGamerscore": 280,
        "maxGamerscore": 1250
    },
    {
        "lastUnlock": "2014-10-25T01:24:26.3798265Z",
        "titleId": 231674300,
        "serviceConfigId": "bee50100-e6da-426e-998e-5f570dcf11bc",
        "titleType": "DGame",
        "platform": "Durango",
        "name": "The Walking Dead: Season Two",
        "earnedAchievements": 40,
        "currentGamerscore": 1000,
        "maxGamerscore": 1000
    },
    {
        "lastUnlock": "2014-09-20T07:10:29.5154023Z",
        "titleId": 238373370,
        "serviceConfigId": "45a30100-6c05-4b9d-8158-0e3b0e3549fa",
        "titleType": "LiveApp",
        "platform": "Durango",
        "name": "FOX NOW",
        "earnedAchievements": 10,
        "currentGamerscore": 0,
        "maxGamerscore": 0
    },
    {
        "lastUnlock": "2015-10-06T06:08:20.8763522Z",
        "titleId": 247546985,
        "serviceConfigId": "37770100-f9ae-4b80-9dad-7c1d0ec14469",
        "titleType": "DGame",
        "platform": "Durango",
        "name": "Destiny",
        "earnedAchievements": 30,
        "currentGamerscore": 715,
        "maxGamerscore": 1500
    },
    {
        "lastUnlock": "2016-11-13T18:26:10.3205760Z",
        "titleId": 252034287,
        "serviceConfigId": "a6df0100-f881-4f82-8997-24630f05bcef",
        "titleType": "DGame",
        "platform": "Durango",
        "name": "The Elder Scrolls V: Skyrim Special Edition",
        "earnedAchievements": 7,
        "currentGamerscore": 85,
        "maxGamerscore": 1550
    },
    {
        "lastUnlock": "2017-06-02T19:07:56.6320000Z",
        "titleId": 256913032,
        "serviceConfigId": "bc670100-2465-4ca9-a3fb-a5dc0f502e88",
        "titleType": "DGame",
        "platform": "Durango",
        "name": "Tekken 7",
        "earnedAchievements": 17,
        "currentGamerscore": 375,
        "maxGamerscore": 1000
    },
    {
        "lastUnlock": "2017-05-30T20:31:37.3540000Z",
        "titleId": 282062756,
        "serviceConfigId": "db140100-e266-468a-ab71-99c610cfefa4",
        "titleType": "DGame",
        "platform": "Durango",
        "name": "The Walking Dead: A New Frontier - Episode 1",
        "earnedAchievements": 30,
        "currentGamerscore": 1000,
        "maxGamerscore": 1000
    },
    {
        "lastUnlock": "2017-06-17T01:06:17.9650000Z",
        "titleId": 301917535,
        "serviceConfigId": "4dae0100-5f8f-4764-b3d6-85c811fee55f",
        "titleType": "DGame",
        "platform": "Durango",
        "name": "Battlefield\u2122 Hardline",
        "earnedAchievements": 20,
        "currentGamerscore": 430,
        "maxGamerscore": 1950
    },
    {
        "lastUnlock": "2017-12-18T05:10:59.4530000Z",
        "titleId": 309834943,
        "serviceConfigId": "aa7a0100-f1b7-4f50-9d01-73491277b4bf",
        "titleType": "DGame",
        "platform": "Durango",
        "name": "Wheel Of Fortune\u00ae",
        "earnedAchievements": 1,
        "currentGamerscore": 50,
        "maxGamerscore": 1000
    },
    {
        "lastUnlock": "2018-02-27T01:42:22.2600000Z",
        "titleId": 320504455,
        "serviceConfigId": "331e0100-3ef1-40a9-87e5-3f84131a8287",
        "titleType": "DGame",
        "platform": "Durango",
        "name": "Middle-earth\u2122: Shadow of War\u2122",
        "earnedAchievements": 32,
        "currentGamerscore": 645,
        "maxGamerscore": 1250
    },
    {
        "lastUnlock": "2015-08-24T06:20:41.3307664Z",
        "titleId": 327370029,
        "serviceConfigId": "595c0100-e535-40c1-93f6-a1b11383452d",
        "titleType": "LiveApp",
        "platform": "Durango",
        "name": "Netflix",
        "earnedAchievements": 7,
        "currentGamerscore": 0,
        "maxGamerscore": 0
    },
    {
        "lastUnlock": "2017-01-22T10:14:47.8060000Z",
        "titleId": 332903703,
        "serviceConfigId": "74ae0100-df7b-407c-8ee3-1bfb13d7b517",
        "titleType": "DGame",
        "platform": "Durango",
        "name": "Fibbage: The Hilarious Bluffing Party Game",
        "earnedAchievements": 9,
        "currentGamerscore": 900,
        "maxGamerscore": 1000
    },
    {
        "lastUnlock": "2017-05-28T04:51:53.4370000Z",
        "titleId": 333628240,
        "serviceConfigId": "636a0100-392d-4116-9c4f-e0c513e2c350",
        "titleType": "DGame",
        "platform": "Durango",
        "name": "Quantum Break",
        "earnedAchievements": 28,
        "currentGamerscore": 635,
        "maxGamerscore": 1000
    },
    {
        "lastUnlock": "2018-02-14T02:04:44.0070000Z",
        "titleId": 338995079,
        "serviceConfigId": "ee020100-fb23-4d3a-8d76-66141434a787",
        "titleType": "DGame",
        "platform": "Durango",
        "name": "Batman: The Enemy Within - Episode 1",
        "earnedAchievements": 24,
        "currentGamerscore": 800,
        "maxGamerscore": 1000
    },
    {
        "lastUnlock": "2017-04-27T06:28:43.4000000Z",
        "titleId": 346683864,
        "serviceConfigId": "7e510100-2b7a-4ca2-b775-46ff14a9f9d8",
        "titleType": "DGame",
        "platform": "Durango",
        "name": "Tom Clancy\u2019s Ghost Recon\u00ae Wildlands - Standard Edition",
        "earnedAchievements": 15,
        "currentGamerscore": 325,
        "maxGamerscore": 1500
    },
    {
        "lastUnlock": "2017-06-24T05:55:07.8300000Z",
        "titleId": 398011207,
        "serviceConfigId": "dca20100-15e7-41fb-b299-64fc17b92b47",
        "titleType": "DGame",
        "platform": "Durango",
        "name": "LIMBO",
        "earnedAchievements": 5,
        "currentGamerscore": 380,
        "maxGamerscore": 1000
    },
    {
        "lastUnlock": "2014-12-05T07:06:40.1696951Z",
        "titleId": 404068970,
        "serviceConfigId": "22520100-11ea-440a-8591-1abd18159a6a",
        "titleType": "LiveApp",
        "platform": "Durango",
        "name": "Comedy Central",
        "earnedAchievements": 8,
        "currentGamerscore": 0,
        "maxGamerscore": 0
    },
    {
        "lastUnlock": "2015-04-05T17:14:19.3556144Z",
        "titleId": 407534069,
        "serviceConfigId": "8dd60100-6cc0-42f2-bb3e-c47b184a79f5",
        "titleType": "DGame",
        "platform": "Durango",
        "name": "Neverwinter",
        "earnedAchievements": 1,
        "currentGamerscore": 5,
        "maxGamerscore": 2470
    },
    {
        "lastUnlock": "2015-09-20T20:53:32.0446993Z",
        "titleId": 417034865,
        "serviceConfigId": "cc370100-2ce1-4b08-bd74-844818db7271",
        "titleType": "LiveApp",
        "platform": "Durango",
        "name": "NFL on Xbox One",
        "earnedAchievements": 5,
        "currentGamerscore": 0,
        "maxGamerscore": 0
    },
    {
        "lastUnlock": "2014-06-24T17:18:42.4412726Z",
        "titleId": 419416564,
        "serviceConfigId": "2cecd28f-3e7f-4239-9047-20d1511b3e08",
        "titleType": "LiveApp",
        "platform": "Durango",
        "name": "Groove Music",
        "earnedAchievements": 1,
        "currentGamerscore": 0,
        "maxGamerscore": 0
    },
    {
        "lastUnlock": "2015-08-04T22:30:14.1336279Z",
        "titleId": 442736763,
        "serviceConfigId": "66eb0100-7c58-4350-b936-f9631a63a07b",
        "titleType": "LiveApp",
        "platform": "Durango",
        "name": "Twitch",
        "earnedAchievements": 10,
        "currentGamerscore": 0,
        "maxGamerscore": 0
    },
    {
        "lastUnlock": "2017-12-22T22:26:16.6090000Z",
        "titleId": 506903100,
        "serviceConfigId": "e8df0100-324d-4c9d-9523-c93b1e36ba3c",
        "titleType": "DGame",
        "platform": "Durango",
        "name": "Madden NFL 18",
        "earnedAchievements": 19,
        "currentGamerscore": 290,
        "maxGamerscore": 1000
    },
    {
        "lastUnlock": "2016-02-28T14:25:06.8341738Z",
        "titleId": 508310328,
        "serviceConfigId": "67ac0100-d8a1-41d2-bfe0-7b0f1e4c3338",
        "titleType": "LiveApp",
        "platform": "Durango",
        "name": "NBC",
        "earnedAchievements": 7,
        "currentGamerscore": 0,
        "maxGamerscore": 0
    },
    {
        "lastUnlock": "2017-10-18T06:33:04.5651812Z",
        "titleId": 552499398,
        "serviceConfigId": "780f0100-3c66-41ff-b8cc-964f20ee78c6",
        "titleType": "DGame",
        "platform": "Durango",
        "name": "Gears of War 4",
        "earnedAchievements": 35,
        "currentGamerscore": 410,
        "maxGamerscore": 3000
    },
    {
        "lastUnlock": "2015-03-31T02:48:44.6533831Z",
        "titleId": 556718860,
        "serviceConfigId": "1658e0c0-e7b7-47a1-9043-60d3a65ea14a",
        "titleType": "DGame",
        "platform": "Durango",
        "name": "Assassin's Creed IV Black Flag",
        "earnedAchievements": 25,
        "currentGamerscore": 505,
        "maxGamerscore": 1250
    },
    {
        "lastUnlock": "2016-12-28T02:44:19.9460000Z",
        "titleId": 559544937,
        "serviceConfigId": "cf540100-ba15-40c8-a416-b6172159fa69",
        "titleType": "DGame",
        "platform": "Durango",
        "name": "Ori and the Blind Forest: Definitive Edition",
        "earnedAchievements": 3,
        "currentGamerscore": 35,
        "maxGamerscore": 1250
    },
    {
        "lastUnlock": "2017-06-17T01:20:59.8510000Z",
        "titleId": 585771792,
        "serviceConfigId": "14a4db43-6853-4bc0-987d-04c54d6f51dc",
        "titleType": "DGame",
        "platform": "Durango",
        "name": "WATCH_DOGS\u2122",
        "earnedAchievements": 1,
        "currentGamerscore": 15,
        "maxGamerscore": 1250
    },
    {
        "lastUnlock": "2017-01-15T06:34:45.2810000Z",
        "titleId": 610345881,
        "serviceConfigId": "e8600100-9a54-4279-9cbd-e12624612399",
        "titleType": "DGame",
        "platform": "Durango",
        "name": "The Jackbox Party Pack",
        "earnedAchievements": 1,
        "currentGamerscore": 50,
        "maxGamerscore": 1000
    },
    {
        "lastUnlock": "2017-02-14T06:30:29.9010000Z",
        "titleId": 651668093,
        "serviceConfigId": "e70c0100-223e-46e4-bfa5-358d26d7aa7d",
        "titleType": "DGame",
        "platform": "Durango",
        "name": "RESIDENT EVIL 7 biohazard",
        "earnedAchievements": 9,
        "currentGamerscore": 140,
        "maxGamerscore": 1620
    },
    {
        "lastUnlock": "2015-03-08T06:23:31.9163921Z",
        "titleId": 666757656,
        "serviceConfigId": "eb970100-1ba4-4575-9fe1-13c827bdea18",
        "titleType": "DGame",
        "platform": "Durango",
        "name": "Rayman Legends",
        "earnedAchievements": 1,
        "currentGamerscore": 10,
        "maxGamerscore": 1000
    },
    {
        "lastUnlock": "2014-02-09T07:02:04.4154418Z",
        "titleId": 682562723,
        "serviceConfigId": "ed240100-924b-4ccc-8f0d-411e28af14a3",
        "titleType": "DGame",
        "platform": "Durango",
        "name": "Halo: Spartan Assault",
        "earnedAchievements": 3,
        "currentGamerscore": 40,
        "maxGamerscore": 1000
    },
    {
        "lastUnlock": "2014-01-12T05:26:44.9148721Z",
        "titleId": 685629307,
        "serviceConfigId": "d56b0100-5205-4049-98c5-ae1e28dddf7b",
        "titleType": "LiveApp",
        "platform": "Durango",
        "name": "FXNOW",
        "earnedAchievements": 7,
        "currentGamerscore": 0,
        "maxGamerscore": 0
    },
    {
        "lastUnlock": "2015-05-01T00:58:56.4476571Z",
        "titleId": 690473296,
        "serviceConfigId": "1b9a0100-4489-4e21-824e-91472927c950",
        "titleType": "LiveApp",
        "platform": "Durango",
        "name": "Nerdist",
        "earnedAchievements": 2,
        "currentGamerscore": 0,
        "maxGamerscore": 0
    },
    {
        "lastUnlock": "2014-11-09T20:22:34.9418893Z",
        "titleId": 694107204,
        "serviceConfigId": "78d50100-4794-4634-9bcb-9d8a295f3c44",
        "titleType": "DGame",
        "platform": "Durango",
        "name": "Dance Central Spotlight",
        "earnedAchievements": 6,
        "currentGamerscore": 95,
        "maxGamerscore": 1000
    },
    {
        "lastUnlock": "2018-02-02T04:35:46.0760000Z",
        "titleId": 735539134,
        "serviceConfigId": "cb190100-e59c-49d6-84fd-e5d12bd76fbe",
        "titleType": "LiveApp",
        "platform": "Durango",
        "name": "The CW",
        "earnedAchievements": 9,
        "currentGamerscore": 0,
        "maxGamerscore": 0
    },
    {
        "lastUnlock": "2018-02-27T22:06:13.1300000Z",
        "titleId": 739464821,
        "serviceConfigId": "2a100100-8bc4-4c84-9afc-15da2c135675",
        "titleType": "DGame",
        "platform": "Durango",
        "name": "South Park\u2122: The Fractured but Whole\u2122",
        "earnedAchievements": 26,
        "currentGamerscore": 730,
        "maxGamerscore": 1000
    },
    {
        "lastUnlock": "2017-01-01T06:31:55.3990000Z",
        "titleId": 767263759,
        "serviceConfigId": "9cf40100-c61f-4a81-a353-d8b12dbb840f",
        "titleType": "DGame",
        "platform": "Durango",
        "name": "Rock Band 4",
        "earnedAchievements": 4,
        "currentGamerscore": 40,
        "maxGamerscore": 1200
    },
    {
        "lastUnlock": "2014-05-05T00:13:16.3853210Z",
        "titleId": 778400368,
        "serviceConfigId": "7b2d6c55-bd7e-4df2-b455-ef0a03f6acfd",
        "titleType": "DGame",
        "platform": "Durango",
        "name": "NBA 2K14",
        "earnedAchievements": 3,
        "currentGamerscore": 20,
        "maxGamerscore": 1000
    },
    {
        "lastUnlock": "2016-02-29T03:45:50.9966553Z",
        "titleId": 830649354,
        "serviceConfigId": "b5fe0100-c634-4d68-870b-7bc83182b40a",
        "titleType": "DGame",
        "platform": "Durango",
        "name": "Dying Light",
        "earnedAchievements": 29,
        "currentGamerscore": 540,
        "maxGamerscore": 1490
    },
    {
        "lastUnlock": "2018-03-10T03:12:54.7780000Z",
        "titleId": 852732437,
        "serviceConfigId": "33ba0100-3d6b-4d38-af1c-cbfb32d3aa15",
        "titleType": "DGame",
        "platform": "Durango",
        "name": "State of Decay: Year-One",
        "earnedAchievements": 10,
        "currentGamerscore": 195,
        "maxGamerscore": 1500
    },
    {
        "lastUnlock": "2016-05-02T23:15:46.6859565Z",
        "titleId": 858615632,
        "serviceConfigId": "f8af4504-af33-427a-807e-4be5d80f72c1",
        "titleType": "DGame",
        "platform": "Durango",
        "name": "Xbox Fitness",
        "earnedAchievements": 4,
        "currentGamerscore": 100,
        "maxGamerscore": 1825
    },
    {
        "lastUnlock": "2014-08-12T02:07:02.0009535Z",
        "titleId": 860666361,
        "serviceConfigId": "80760100-b3cf-4a48-aa85-5811334cb9f9",
        "titleType": "DGame",
        "platform": "Durango",
        "name": "Plants vs. Zombies Garden Warfare",
        "earnedAchievements": 15,
        "currentGamerscore": 235,
        "maxGamerscore": 1500
    },
    {
        "lastUnlock": "2017-04-29T09:01:04.8710000Z",
        "titleId": 862712929,
        "serviceConfigId": "ca310100-b8de-4079-83fd-3e58336bf461",
        "titleType": "DGame",
        "platform": "Durango",
        "name": "Star Trek Online",
        "earnedAchievements": 1,
        "currentGamerscore": 10,
        "maxGamerscore": 1090
    },
    {
        "lastUnlock": "2014-08-24T04:45:28.0234204Z",
        "titleId": 874889576,
        "serviceConfigId": "502e0100-78e0-4fea-a178-e6a33425c168",
        "titleType": "LiveApp",
        "platform": "Durango",
        "name": "Amazon Instant Video",
        "earnedAchievements": 1,
        "currentGamerscore": 0,
        "maxGamerscore": 0
    },
    {
        "lastUnlock": "2014-12-30T04:32:43.3111736Z",
        "titleId": 972022825,
        "serviceConfigId": "db580100-a1b3-4f03-8a1a-75f439efe429",
        "titleType": "DGame",
        "platform": "Durango",
        "name": "Tetris\u00ae Ultimate",
        "earnedAchievements": 1,
        "currentGamerscore": 25,
        "maxGamerscore": 1000
    },
    {
        "lastUnlock": "2015-08-10T03:28:20.3467588Z",
        "titleId": 972249091,
        "serviceConfigId": "b7b6df83-54f9-46ee-b1ec-95bbae5171db",
        "titleType": "DGame",
        "platform": "Durango",
        "name": "Grand Theft Auto V",
        "earnedAchievements": 31,
        "currentGamerscore": 485,
        "maxGamerscore": 1750
    },
    {
        "lastUnlock": "2015-04-12T03:26:20.7872470Z",
        "titleId": 974494926,
        "serviceConfigId": "c6d20100-30ea-4e3f-8136-7a0b3a159cce",
        "titleType": "LiveApp",
        "platform": "Durango",
        "name": "Hulu",
        "earnedAchievements": 9,
        "currentGamerscore": 0,
        "maxGamerscore": 0
    },
    {
        "lastUnlock": "2017-12-17T20:29:30.2490000Z",
        "titleId": 975485641,
        "serviceConfigId": "616c0100-aa9a-48d1-9161-02f83a24bac9",
        "titleType": "DGame",
        "platform": "Durango",
        "name": "Back to the Future: The Game - 30th Anniversary Edition",
        "earnedAchievements": 2,
        "currentGamerscore": 25,
        "maxGamerscore": 1000
    },
    {
        "lastUnlock": "2015-09-06T19:53:31.5509119Z",
        "titleId": 976905576,
        "serviceConfigId": "e8e80100-1c04-410c-a9e5-41bc3a3a6568",
        "titleType": "DGame",
        "platform": "Durango",
        "name": "Dragon Age\u2122: Inquisition",
        "earnedAchievements": 14,
        "currentGamerscore": 210,
        "maxGamerscore": 1570
    },
    {
        "lastUnlock": "2015-04-25T22:44:45.0629899Z",
        "titleId": 1008687929,
        "serviceConfigId": "1a930100-429f-476c-bfaf-f01b3c1f5b39",
        "titleType": "DGame",
        "platform": "Durango",
        "name": "Mortal Kombat X",
        "earnedAchievements": 10,
        "currentGamerscore": 150,
        "maxGamerscore": 1500
    },
    {
        "lastUnlock": "2017-06-27T02:44:21.9760000Z",
        "titleId": 1022544763,
        "serviceConfigId": "43ce0100-a619-4340-9aef-ed1e3cf2cb7b",
        "titleType": "DGame",
        "platform": "Durango",
        "name": "HITMAN\u2122",
        "earnedAchievements": 11,
        "currentGamerscore": 180,
        "maxGamerscore": 1360
    },
    {
        "lastUnlock": "2017-12-01T07:49:00.3170000Z",
        "titleId": 1029188769,
        "serviceConfigId": "7efb0100-7f2a-4585-9ed5-20a63d582ca1",
        "titleType": "DGame",
        "platform": "Durango",
        "name": "Marvel\u2019s Guardians of the Galaxy: The Telltale Series - Episode 1",
        "earnedAchievements": 30,
        "currentGamerscore": 1000,
        "maxGamerscore": 1000
    },
    {
        "lastUnlock": "2017-04-27T21:34:51.1320000Z",
        "titleId": 1030018025,
        "serviceConfigId": "6fa90100-88a3-442b-a8b1-8cf53d64d3e9",
        "titleType": "DGame",
        "platform": "Durango",
        "name": "Halo Wars: Definitive Edition",
        "earnedAchievements": 3,
        "currentGamerscore": 35,
        "maxGamerscore": 1500
    },
    {
        "lastUnlock": "2016-04-16T01:30:13.5376647Z",
        "titleId": 1030770725,
        "serviceConfigId": "d21e9244-9bd8-49bf-b00e-605e586249a5",
        "titleType": "LiveApp",
        "platform": "Durango",
        "name": "Movies & TV",
        "earnedAchievements": 2,
        "currentGamerscore": 0,
        "maxGamerscore": 0
    },
    {
        "lastUnlock": "2015-01-19T01:34:05.2712807Z",
        "titleId": 1033012343,
        "serviceConfigId": "2f4e194d-16b5-47c3-b7e8-ec284282a67a",
        "titleType": "DGame",
        "platform": "Durango",
        "name": "D4: Dark Dreams Don't Die",
        "earnedAchievements": 2,
        "currentGamerscore": 10,
        "maxGamerscore": 1000
    },
    {
        "lastUnlock": "2017-12-25T21:00:10.5640000Z",
        "titleId": 1044501532,
        "serviceConfigId": "d5a10100-9369-484e-acdb-b9953e41d41c",
        "titleType": "DGame",
        "platform": "Durango",
        "name": "Jeopardy!",
        "earnedAchievements": 1,
        "currentGamerscore": 50,
        "maxGamerscore": 1000
    },
    {
        "lastUnlock": "2015-05-31T08:05:15.3526354Z",
        "titleId": 1144039928,
        "serviceConfigId": "77290100-225e-4768-9373-98164430a9f8",
        "titleType": "DGame",
        "platform": "Durango",
        "name": "Halo: The Master Chief Collection",
        "earnedAchievements": 66,
        "currentGamerscore": 565,
        "maxGamerscore": 6000
    },
    {
        "lastUnlock": "2016-11-11T23:26:27.6698465Z",
        "titleId": 1145574011,
        "serviceConfigId": "387a0100-dd3f-4dd2-9471-88134448127b",
        "titleType": "DGame",
        "platform": "Durango",
        "name": "Titanfall\u00ae 2",
        "earnedAchievements": 32,
        "currentGamerscore": 570,
        "maxGamerscore": 1000
    },
    {
        "lastUnlock": "2016-11-26T20:48:34.7220000Z",
        "titleId": 1175562227,
        "serviceConfigId": "de480100-8417-4199-91fe-b2a84611a7f3",
        "titleType": "DGame",
        "platform": "Durango",
        "name": "Just Cause 3",
        "earnedAchievements": 1,
        "currentGamerscore": 10,
        "maxGamerscore": 1605
    },
    {
        "lastUnlock": "2015-07-18T14:59:12.5884141Z",
        "titleId": 1234432164,
        "serviceConfigId": "6baf0100-d410-4d3c-afd5-68bd4993f0a4",
        "titleType": "DGame",
        "platform": "Durango",
        "name": "EA SPORTS\u2122 Rory McIlroy PGA TOUR\u00ae",
        "earnedAchievements": 4,
        "currentGamerscore": 85,
        "maxGamerscore": 1000
    },
    {
        "lastUnlock": "2015-09-01T05:04:08.2120344Z",
        "titleId": 1249526091,
        "serviceConfigId": "33480100-cb54-4451-8a00-6ee14a7a414b",
        "titleType": "DGame",
        "platform": "Durango",
        "name": "Madden NFL 16",
        "earnedAchievements": 10,
        "currentGamerscore": 145,
        "maxGamerscore": 1000
    },
    {
        "lastUnlock": "2016-09-03T17:35:46.4700000Z",
        "titleId": 1260456400,
        "serviceConfigId": "8f9d0100-d5cc-4790-a2a8-c6a64b2109d0",
        "titleType": "DGame",
        "platform": "Durango",
        "name": "Earthlock: Festival of Magic",
        "earnedAchievements": 2,
        "currentGamerscore": 20,
        "maxGamerscore": 1000
    },
    {
        "lastUnlock": "2017-12-02T08:11:24.2070000Z",
        "titleId": 1278892798,
        "serviceConfigId": "afa10100-73f8-4d17-af58-f4f84c3a5afe",
        "titleType": "DGame",
        "platform": "Durango",
        "name": "TRIVIAL PURSUIT LIVE!",
        "earnedAchievements": 2,
        "currentGamerscore": 75,
        "maxGamerscore": 1000
    },
    {
        "lastUnlock": "2017-06-24T21:35:01.1690000Z",
        "titleId": 1285166951,
        "serviceConfigId": "dd7a0100-915c-4cc6-935b-f67e4c9a1767",
        "titleType": "DGame",
        "platform": "Durango",
        "name": "The Elder Scrolls Online: Tamriel Unlimited",
        "earnedAchievements": 4,
        "currentGamerscore": 20,
        "maxGamerscore": 2960
    },
    {
        "lastUnlock": "2014-04-14T02:43:15.0482105Z",
        "titleId": 1292135256,
        "serviceConfigId": "7d0597d8-2113-423a-9e4f-ed725b9d43ba",
        "titleType": "DGame",
        "platform": "Durango",
        "name": "Titanfall",
        "earnedAchievements": 25,
        "currentGamerscore": 725,
        "maxGamerscore": 2000
    },
    {
        "lastUnlock": "2014-07-12T17:42:25.5014446Z",
        "titleId": 1302301894,
        "serviceConfigId": "c782d0d4-202f-48d1-894d-93a757e85f4f",
        "titleType": "DGame",
        "platform": "Durango",
        "name": "Powerstar Golf",
        "earnedAchievements": 12,
        "currentGamerscore": 135,
        "maxGamerscore": 1250
    },
    {
        "lastUnlock": "2014-10-17T00:41:12.2614548Z",
        "titleId": 1343920370,
        "serviceConfigId": "523f0100-8085-44f5-a86a-131c501a98f2",
        "titleType": "DGame",
        "platform": "Durango",
        "name": "NBA 2K15",
        "earnedAchievements": 3,
        "currentGamerscore": 25,
        "maxGamerscore": 1000
    },
    {
        "lastUnlock": "2016-11-27T05:22:45.7010000Z",
        "titleId": 1386529057,
        "serviceConfigId": "72010100-7d7f-4105-b34e-3ec552a4c121",
        "titleType": "DGame",
        "platform": "Durango",
        "name": "Battlefield\u2122 1",
        "earnedAchievements": 6,
        "currentGamerscore": 60,
        "maxGamerscore": 2000
    },
    {
        "lastUnlock": "2015-09-07T04:17:51.1067180Z",
        "titleId": 1475571605,
        "serviceConfigId": "8e4a0100-1d0e-4885-b99e-7f3f57f36f95",
        "titleType": "DGame",
        "platform": "Durango",
        "name": "Gears of War: Ultimate Edition",
        "earnedAchievements": 30,
        "currentGamerscore": 620,
        "maxGamerscore": 1250
    },
    {
        "lastUnlock": "2015-08-12T22:32:08.5093902Z",
        "titleId": 1479758055,
        "serviceConfigId": "bedbd988-e7f9-4523-9ad5-a3bbc92658a5",
        "titleType": "DGame",
        "platform": "Durango",
        "name": "Batman\u2122: Arkham Knight",
        "earnedAchievements": 57,
        "currentGamerscore": 910,
        "maxGamerscore": 2000
    },
    {
        "lastUnlock": "2014-02-09T06:15:27.5608921Z",
        "titleId": 1484511986,
        "serviceConfigId": "d2a649c9-5d53-4b5c-8c62-89d87d074cf6",
        "titleType": "DGame",
        "platform": "Durango",
        "name": "Battlefield 4",
        "earnedAchievements": 19,
        "currentGamerscore": 395,
        "maxGamerscore": 1600
    },
    {
        "lastUnlock": "2015-04-13T02:12:15.4168925Z",
        "titleId": 1512517621,
        "serviceConfigId": "d7790100-eaf5-4d63-ba33-97365a272ff5",
        "titleType": "DGame",
        "platform": "Durango",
        "name": "Child of Light",
        "earnedAchievements": 1,
        "currentGamerscore": 20,
        "maxGamerscore": 1000
    },
    {
        "lastUnlock": "2015-04-03T01:26:50.0990616Z",
        "titleId": 1519874468,
        "serviceConfigId": "1b180100-2e72-4297-a9e6-b79d5a9771a4",
        "titleType": "DGame",
        "platform": "Durango",
        "name": "Forza Horizon 2 Presents Fast & Furious",
        "earnedAchievements": 3,
        "currentGamerscore": 140,
        "maxGamerscore": 1000
    },
    {
        "lastUnlock": "2016-04-17T05:28:30.1452515Z",
        "titleId": 1579532320,
        "serviceConfigId": "88222fc5-b30c-43f2-ab0f-834e9b2266c4",
        "titleType": "DGame",
        "platform": "Durango",
        "name": "Sunset Overdrive",
        "earnedAchievements": 2,
        "currentGamerscore": 40,
        "maxGamerscore": 1925
    },
    {
        "lastUnlock": "2017-04-22T22:38:49.7460000Z",
        "titleId": 1590411380,
        "serviceConfigId": "286f0100-6f0e-466d-a793-f6455ecbc074",
        "titleType": "DGame",
        "platform": "Durango",
        "name": "Mass Effect\u2122: Andromeda",
        "earnedAchievements": 16,
        "currentGamerscore": 210,
        "maxGamerscore": 1000
    },
    {
        "lastUnlock": "2014-03-24T19:01:47.4514752Z",
        "titleId": 1616270757,
        "serviceConfigId": "d18e0100-f3b7-41d9-a140-cd37605655a5",
        "titleType": "DGame",
        "platform": "Durango",
        "name": "NBA LIVE 14",
        "earnedAchievements": 2,
        "currentGamerscore": 30,
        "maxGamerscore": 1000
    },
    {
        "lastUnlock": "2014-08-13T02:57:01.8507583Z",
        "titleId": 1649675719,
        "serviceConfigId": "f91e0100-f415-4989-9ff5-115462540dc7",
        "titleType": "DGame",
        "platform": "Durango",
        "name": "Max: The Curse of Brotherhood",
        "earnedAchievements": 9,
        "currentGamerscore": 155,
        "maxGamerscore": 1000
    },
    {
        "lastUnlock": "2017-05-04T20:58:08.7450000Z",
        "titleId": 1667928394,
        "serviceConfigId": "e7c70100-92e8-4a04-8b33-b9f8636a914a",
        "titleType": "DGame",
        "platform": "Durango",
        "name": "Halo Wars 2",
        "earnedAchievements": 27,
        "currentGamerscore": 330,
        "maxGamerscore": 1750
    },
    {
        "lastUnlock": "2015-11-22T22:30:55.0969852Z",
        "titleId": 1681220621,
        "serviceConfigId": "126a0100-20f4-4dfc-a88d-0bf26435640d",
        "titleType": "DGame",
        "platform": "Durango",
        "name": "STAR WARS\u2122 Battlefront\u2122",
        "earnedAchievements": 6,
        "currentGamerscore": 90,
        "maxGamerscore": 1690
    },
    {
        "lastUnlock": "2014-08-21T08:14:54.0000000Z",
        "titleId": 1708767297,
        "serviceConfigId": "25629596-d386-444c-a82e-734960c1dea3",
        "titleType": "DGame",
        "platform": "Durango",
        "name": "Ryse: Son of Rome",
        "earnedAchievements": 49,
        "currentGamerscore": 1150,
        "maxGamerscore": 2000
    },
    {
        "lastUnlock": "2014-10-23T00:14:13.9217576Z",
        "titleId": 1795379754,
        "serviceConfigId": "b11d0100-eb84-4b9b-bf61-2dc96b03522a",
        "titleType": "DGame",
        "platform": "Durango",
        "name": "The Walking Dead: The Complete First Season",
        "earnedAchievements": 46,
        "currentGamerscore": 955,
        "maxGamerscore": 1000
    },
    {
        "lastUnlock": "2016-01-11T07:24:30.3564817Z",
        "titleId": 1799887933,
        "serviceConfigId": "de360100-3ae5-4fd5-a7da-9d3d6b481c3d",
        "titleType": "DGame",
        "platform": "Durango",
        "name": "The Witcher 3: Wild Hunt",
        "earnedAchievements": 27,
        "currentGamerscore": 500,
        "maxGamerscore": 2000
    },
    {
        "lastUnlock": "2018-03-08T06:00:31.3610000Z",
        "titleId": 1835497756,
        "serviceConfigId": "6d6f0100-dc13-45c3-a35e-5c9a6d67791c",
        "titleType": "DGame",
        "platform": "Durango",
        "name": "Agents of Mayhem",
        "earnedAchievements": 6,
        "currentGamerscore": 80,
        "maxGamerscore": 1000
    },
    {
        "lastUnlock": "2017-05-31T19:37:21.5590000Z",
        "titleId": 1839786246,
        "serviceConfigId": "e1610100-3804-4f0b-a29f-0c606da8e906",
        "titleType": "DGame",
        "platform": "Durango",
        "name": "Murdered: Soul Suspect",
        "earnedAchievements": 10,
        "currentGamerscore": 150,
        "maxGamerscore": 1000
    },
    {
        "lastUnlock": "2017-05-19T02:32:12.6890000Z",
        "titleId": 1856172970,
        "serviceConfigId": "89c70100-7c9c-47b0-8979-65676ea2f3aa",
        "titleType": "DGame",
        "platform": "Durango",
        "name": "Game of Thrones - Episode 1: Iron from Ice",
        "earnedAchievements": 48,
        "currentGamerscore": 1000,
        "maxGamerscore": 1000
    },
    {
        "lastUnlock": "2015-07-12T08:36:27.4262702Z",
        "titleId": 1891324329,
        "serviceConfigId": "8a1b0100-48ca-4c67-abcc-1ae170bb51a9",
        "titleType": "LiveApp",
        "platform": "Durango",
        "name": "VUDU Movies & TV",
        "earnedAchievements": 4,
        "currentGamerscore": 0,
        "maxGamerscore": 0
    },
    {
        "lastUnlock": "2016-01-18T00:43:18.2871915Z",
        "titleId": 1906672574,
        "serviceConfigId": "5674e1ad-ee96-444d-bedc-5ec795b1e772",
        "titleType": "DGame",
        "platform": "Durango",
        "name": "Middle-earth\u2122: Shadow of Mordor\u2122",
        "earnedAchievements": 36,
        "currentGamerscore": 735,
        "maxGamerscore": 1680
    },
    {
        "lastUnlock": "2015-03-14T05:58:31.6048616Z",
        "titleId": 1918441274,
        "serviceConfigId": "2d660100-78ab-444e-bef1-71327259173a",
        "titleType": "DGame",
        "platform": "Durango",
        "name": "MONOPOLY PLUS",
        "earnedAchievements": 8,
        "currentGamerscore": 380,
        "maxGamerscore": 1000
    },
    {
        "lastUnlock": "2016-06-21T03:41:18.5639959Z",
        "titleId": 1979014977,
        "serviceConfigId": "45a60100-cd32-4650-95a7-2ba075f55f41",
        "titleType": "DGame",
        "platform": "Durango",
        "name": "The Crew",
        "earnedAchievements": 1,
        "currentGamerscore": 15,
        "maxGamerscore": 1000
    },
    {
        "lastUnlock": "2014-05-20T05:28:30.4134361Z",
        "titleId": 1999803984,
        "serviceConfigId": "66960100-1f61-49b0-9fd2-ea4077329650",
        "titleType": "DGame",
        "platform": "Durango",
        "name": "The Amazing Spider-Man 2\u2122",
        "earnedAchievements": 26,
        "currentGamerscore": 545,
        "maxGamerscore": 1000
    },
    {
        "lastUnlock": "2017-07-15T07:02:13.4470000Z",
        "titleId": 2014880780,
        "serviceConfigId": "b70e0100-81fd-4489-af21-78087818a40c",
        "titleType": "DGame",
        "platform": "Durango",
        "name": "Madden NFL 17",
        "earnedAchievements": 11,
        "currentGamerscore": 295,
        "maxGamerscore": 1000
    },
    {
        "lastUnlock": "2014-07-22T07:13:04.9006245Z",
        "titleId": 2067126551,
        "serviceConfigId": "a72e0e3d-ce31-4ae0-89b8-741c625ab197",
        "titleType": "DGame",
        "platform": "Durango",
        "name": "Forza Motorsport 5",
        "earnedAchievements": 18,
        "currentGamerscore": 185,
        "maxGamerscore": 1400
    },
    {
        "lastUnlock": "2017-02-08T02:40:25.1920000Z",
        "titleId": 2142027917,
        "serviceConfigId": "00000000-0000-0000-0000-00007facc08d",
        "titleType": "Game",
        "platform": "XboxOne",
        "name": "Fallout Shelter",
        "earnedAchievements": 1,
        "currentGamerscore": 10,
        "maxGamerscore": 1000
    },
    {
        "lastUnlock": "2014-12-14T18:59:35.9369314Z",
        "titleId": 2147358433,
        "serviceConfigId": "28360100-1f6f-4a8d-b425-4dbd7ffe16e1",
        "titleType": "DGame",
        "platform": "Durango",
        "name": "Madden NFL 15",
        "earnedAchievements": 5,
        "currentGamerscore": 85,
        "maxGamerscore": 1000
    }
]